roa_collector/__init__.py
roa_collector/__main__.py
roa_collector/roa_collector.py
roa_collector/test/__init__.py
roa_collector/test/test_roa_collector.py
roa_collector-2.0.9.dist-info/licenses/LICENSE.txt
roa_collector-2.0.9.dist-info/METADATA
roa_collector-2.0.9.dist-info/WHEEL
roa_collector-2.0.9.dist-info/entry_points.txt
roa_collector-2.0.9.dist-info/top_level.txt
roa_collector-2.0.9.dist-info/RECORD
