Metadata-Version: 2.4
Name: roa_collector
Version: 2.0.9
Summary: Downloads ROA info solely for research purposes
Author-email: Justin Furuness <jfuruness@gmail.com>, Arvind Kasiliya <arvind.kasiliya@uconn.edu>
License: Copyright 2020 Justin Furuness
Project-URL: homepage, https://github.com/jfuruness/roa_collector.git
Keywords: Furuness,BGP,Hijack,ROA,ROV
Classifier: Programming Language :: Python :: 3.10
Classifier: Programming Language :: Python :: 3.11
Classifier: Programming Language :: Python :: 3.12
Classifier: Programming Language :: Python :: 3.13
Classifier: Programming Language :: Python :: 3.14
Classifier: Programming Language :: Python :: Implementation :: CPython
Classifier: Programming Language :: Python :: Implementation :: PyPy
Classifier: Environment :: Console
Classifier: License :: OSI Approved :: BSD License
Classifier: Intended Audience :: Developers
Classifier: Operating System :: POSIX :: Linux
Classifier: Operating System :: MacOS
Classifier: Operating System :: MacOS :: MacOS X
Classifier: Topic :: Security
Requires-Python: >=3.10
License-File: LICENSE.txt
Requires-Dist: roa_checker~=3.0
Requires-Dist: requests-cache==1.2.1
Requires-Dist: platformdirs==4.5.1
Provides-Extra: test
Requires-Dist: pytest==9.0.2; extra == "test"
Requires-Dist: pre-commit==4.5.1; extra == "test"
Requires-Dist: mypy==1.19.1; extra == "test"
Requires-Dist: tox==4.34.1; extra == "test"
Requires-Dist: ruff==0.14.13; extra == "test"
Requires-Dist: types-requests==2.32.4.20260107; extra == "test"
Dynamic: license-file
